langgraph_codeact-0.1.3.dist-info/METADATA
langgraph_codeact-0.1.3.dist-info/WHEEL
langgraph_codeact-0.1.3.dist-info/entry_points.txt
langgraph_codeact-0.1.3.dist-info/licenses/LICENSE
langgraph_codeact/__init__.py
langgraph_codeact/utils.py
langgraph_codeact-0.1.3.dist-info/RECORD
