Metadata-Version: 2.1
Name: langgraph-codeact
Version: 0.1.3
Summary: LangGraph implementation of CodeAct agent that generates and executes code instead of tool calling.
Author-Email: Nuno Campos <nuno@langchain.dev>
License: MIT
Requires-Python: <4.0,>=3.10
Requires-Dist: langgraph<0.4.0,>=0.3.5
